code_review_agent/__init__.py
code_review_agent/agent.py
code_review_agent/cli.py
code_review_agent/constants.py
code_review_agent/gitignore.py
code_review_agent/progress.py
code_review_agent/state.py
code_review_agent/llm/__init__.py
code_review_agent/llm/base.py
code_review_agent/llm/claude_agent.py
code_review_agent/llm/gemini_agent.py
code_review_agent-0.4.1.dist-info/METADATA
code_review_agent-0.4.1.dist-info/WHEEL
code_review_agent-0.4.1.dist-info/entry_points.txt
code_review_agent-0.4.1.dist-info/RECORD
