Metadata-Version: 2.4
Name: code-review-agent
Version: 0.4.1
Summary: Intelligent code review tool supporting Claude and Gemini
Requires-Python: >=3.10
Requires-Dist: aiofiles>=24.1.0
Requires-Dist: claude-agent-sdk>=0.1.18
Requires-Dist: click>=8.3.1
Requires-Dist: pathspec>=1.0.0
Provides-Extra: dev
Requires-Dist: mypy>=1.13.0; extra == 'dev'
Requires-Dist: pytest-asyncio>=0.24.0; extra == 'dev'
Requires-Dist: pytest>=8.0.0; extra == 'dev'
Requires-Dist: ruff>=0.8.0; extra == 'dev'
